LICENSE
MANIFEST.in
Makefile
setup.cfg
setup.py
Flask_ICU.egg-info/PKG-INFO
Flask_ICU.egg-info/SOURCES.txt
Flask_ICU.egg-info/dependency_links.txt
Flask_ICU.egg-info/not-zip-safe
Flask_ICU.egg-info/requires.txt
Flask_ICU.egg-info/top_level.txt
flask_icu/__init__.py
flask_icu/_compat.py
tests/babel.cfg
tests/messages.pot
tests/tests.py
tests/translations/de/messages.json
tests/translations/en/messages.json